flamingo_pytorch/__init__.py
flamingo_pytorch/flamingo_palm.py
flamingo_pytorch/flamingo_pytorch.py
flamingo_pytorch-0.1.2.dist-info/LICENSE
flamingo_pytorch-0.1.2.dist-info/METADATA
flamingo_pytorch-0.1.2.dist-info/WHEEL
flamingo_pytorch-0.1.2.dist-info/top_level.txt
flamingo_pytorch-0.1.2.dist-info/RECORD
