Metadata-Version: 2.1
Name: flamingo-pytorch
Version: 0.1.2
Summary: Flamingo - Pytorch
Home-page: https://github.com/lucidrains/flamingo-pytorch
Author: Phil Wang
Author-email: lucidrains@gmail.com
License: MIT
Keywords: artificial intelligence,deep learning,transformers,attention mechanism,visual question answering
Classifier: Development Status :: 4 - Beta
Classifier: Intended Audience :: Developers
Classifier: Topic :: Scientific/Engineering :: Artificial Intelligence
Classifier: License :: OSI Approved :: MIT License
Classifier: Programming Language :: Python :: 3.6
License-File: LICENSE
Requires-Dist: einops (>=0.4)
Requires-Dist: einops-exts
Requires-Dist: torch (>=1.6)
